signal_grad_cam/__init__.py
signal_grad_cam/cam_builder.py
signal_grad_cam/pytorch_cam_builder.py
signal_grad_cam/tensorflow_cam_builder.py
signal_grad_cam-2.0.0.dist-info/LICENSE
signal_grad_cam-2.0.0.dist-info/METADATA
signal_grad_cam-2.0.0.dist-info/WHEEL
signal_grad_cam-2.0.0.dist-info/top_level.txt
signal_grad_cam-2.0.0.dist-info/RECORD
