Metadata-Version: 2.1
Name: signal_grad_cam
Version: 2.0.0
Summary: SignalGrad-CAM aims at generalising Grad-CAM to one-dimensional applications, while enhancing usability and efficiency.
Home-page: https://github.com/samuelepe11/signal_grad_cam
Author: Samuele Pe
Author-email: samuele.pe01@universitadipavia.it
License: MIT
Keywords: XAI,class activation maps,CNN,time series
Classifier: License :: OSI Approved :: MIT License
Classifier: Operating System :: OS Independent
Classifier: Programming Language :: Python :: 3.11
Requires-Python: >=3.11
License-File: LICENSE
Requires-Dist: numpy
Requires-Dist: matplotlib
Requires-Dist: opencv-python
Requires-Dist: torch
Requires-Dist: keras
Requires-Dist: tensorflow
Requires-Dist: imageio
